claptrap/__init__.py
claptrap/backports.py
claptrap/canned.py
claptrap/dumps.py
claptrap/munging.py
claptrap/phrasegenerator.py
claptrap/scripts.py
claptrap/serializer.py
claptrap/data/dracula.claptrap.gz
claptrap-0.2.0.dist-info/METADATA
claptrap-0.2.0.dist-info/RECORD
claptrap-0.2.0.dist-info/WHEEL
claptrap-0.2.0.dist-info/entry_points.txt
claptrap-0.2.0.dist-info/top_level.txt
