Metadata-Version: 2.1
Name: claptrap
Version: 0.2.0
Summary: Spew words using bigram frequencies
Home-page: https://github.com/nicktimko/claptrap
Author: Nick Timkovich
Author-email: prometheus235@gmail.com
License: MIT
Platform: UNKNOWN
Classifier: Development Status :: 3 - Alpha
Classifier: License :: OSI Approved :: MIT License
Classifier: Programming Language :: Python :: 3
